flexiai/__init__.py
flexiai/assistant_actions/__init__.py
flexiai/assistant_actions/functions_manager.py
flexiai/assistant_actions/functions_registry.py
flexiai/cfg/__init__.py
flexiai/cfg/config.py
flexiai/cfg/logging_config.py
flexiai/core/__init__.py
flexiai/core/flexiai_client.py
flexiai/core/flexi_managers/__init__.py
flexiai/core/flexi_managers/assistant_manager.py
flexiai/core/flexi_managers/audio_manager.py
flexiai/core/flexi_managers/completions_manager.py
flexiai/core/flexi_managers/embedding_manager.py
flexiai/core/flexi_managers/images_manager.py
flexiai/core/flexi_managers/local_vector_store_manager.py
flexiai/core/flexi_managers/message_manager.py
flexiai/core/flexi_managers/multi_agent_system.py
flexiai/core/flexi_managers/run_manager.py
flexiai/core/flexi_managers/session_manager.py
flexiai/core/flexi_managers/stream_event_handler.py
flexiai/core/flexi_managers/thread_manager.py
flexiai/core/flexi_managers/vector_store_manager.py
flexiai/core/utils/__init__.py
flexiai/core/utils/helpers.py
flexiai/credentials/__init__.py
flexiai/credentials/azure_openai_credential_strategy.py
flexiai/credentials/credential_manager.py
flexiai/credentials/credential_strategy.py
flexiai/credentials/openai_credential_strategy.py
flexiai/scripts/__init__.py
flexiai/scripts/cli.py
flexiai/scripts/flexiai_basic_flask_app.py
flexiai/scripts/flexiai_rag_extension.py
flexi_actions-0.0.1.dist-info/LICENSE
flexi_actions-0.0.1.dist-info/METADATA
flexi_actions-0.0.1.dist-info/WHEEL
flexi_actions-0.0.1.dist-info/entry_points.txt
flexi_actions-0.0.1.dist-info/top_level.txt
flexi_actions-0.0.1.dist-info/RECORD
