Metadata-Version: 2.1
Name: flexi_actions
Version: 0.0.1
Summary: FlexiAI: A dynamic and modular AI framework leveraging Multi-Agent Systems and Retrieval Augmented Generation (RAG) for seamless integration with OpenAI and Azure OpenAI services.
Home-page: https://github.com/SavinRazvan/flexiai
Author: Savin Ionut Razvan
Author-email: razvan.i.savin@gmail.com
License: MIT
Project-URL: Bug Reports, https://github.com/SavinRazvan/flexiai/issues
Project-URL: Source, https://github.com/SavinRazvan/flexiai
Classifier: Programming Language :: Python :: 3.10
Classifier: Programming Language :: Python :: 3.11
Classifier: Programming Language :: Python :: 3.12
Classifier: Programming Language :: Python :: 3.13
Classifier: License :: OSI Approved :: MIT License
Classifier: Operating System :: OS Independent
Classifier: Development Status :: 7 - Inactive
Classifier: Intended Audience :: Science/Research
Classifier: Topic :: Software Development
Requires-Python: >=3.10
License-File: LICENSE
Requires-Dist: annotated-types<0.8.0,>=0.7.0
Requires-Dist: anyio<5.0.0,>=4.4.0
Requires-Dist: azure-common<2.0.0,>=1.1.28
Requires-Dist: azure-core<2.0.0,>=1.30.2
Requires-Dist: azure-identity<2.0.0,>=1.17.1
Requires-Dist: azure-mgmt-core<2.0.0,>=1.4.0
Requires-Dist: azure-mgmt-resource<24.0.0,>=23.1.1
Requires-Dist: blinker<2.0.0,>=1.8.2
Requires-Dist: certifi<2025.0.0,>=2024.7.4
Requires-Dist: cffi<2.0.0,>=1.16.0
Requires-Dist: charset-normalizer<4.0.0,>=3.3.2
Requires-Dist: click<9.0.0,>=8.1.7
Requires-Dist: cryptography<44.0.0,>=43.0.0
Requires-Dist: distro<2.0.0,>=1.9.0
Requires-Dist: Flask<4.0.0,>=3.0.3
Requires-Dist: h11<0.15.0,>=0.14.0
Requires-Dist: httpcore<2.0.0,>=1.0.5
Requires-Dist: httpx<0.28.0,>=0.27.0
Requires-Dist: idna<4.0.0,>=3.7
Requires-Dist: iniconfig<3.0.0,>=2.0.0
Requires-Dist: isodate<1.0.0,>=0.6.1
Requires-Dist: itsdangerous<3.0.0,>=2.2.0
Requires-Dist: Jinja2<4.0.0,>=3.1.4
Requires-Dist: MarkupSafe<4.0.0,>=2.1.5
Requires-Dist: msal<2.0.0,>=1.30.0
Requires-Dist: msal-extensions<2.0.0,>=1.2.0
Requires-Dist: nest-asyncio<2.0.0,>=1.6.0
Requires-Dist: openai<2.0.0,>=1.51.0
Requires-Dist: packaging<25.0,>=24.1
Requires-Dist: platformdirs<5.0.0,>=3.7.0
Requires-Dist: pluggy<2.0.0,>=1.5.0
Requires-Dist: portalocker<3.0.0,>=2.10.1
Requires-Dist: pycparser<3.0.0,>=2.22
Requires-Dist: pydantic<3.0.0,>=2.8.2
Requires-Dist: pydantic-settings<3.0.0,>=2.3.3
Requires-Dist: pydantic-core<3.0.0,>=2.20.1
Requires-Dist: PyJWT<3.0.0,>=2.8.0
Requires-Dist: pytest<9.0.0,>=8.3.1
Requires-Dist: python-dotenv<2.0.0,>=1.0.1
Requires-Dist: pillow<11.0.0,>=10.4.0
Requires-Dist: pypandoc<2.0.0,>=1.13
Requires-Dist: requests<3.0.0,>=2.32.3
Requires-Dist: six<2.0.0,>=1.16.0
Requires-Dist: sniffio<2.0.0,>=1.3.1
Requires-Dist: tqdm<5.0.0,>=4.66.4
Requires-Dist: typing-extensions<5.0.0,>=4.12.2
Requires-Dist: urllib3<3.0.0,>=2.2.2
Requires-Dist: Werkzeug<4.0.0,>=3.0.3
Requires-Dist: faiss-cpu<2.0.0,>=1.8.0
Requires-Dist: numpy<2.0.0,>=1.26.4
